src/__init__.py
src/__main__.py
src/__version__.py
src/processor.py
src/settings.py
src/usage.py
src/git_tools/__init__.py
src/git_tools/git_repo.py
src/models/__init__.py
src/models/_base_def.py
src/models/application.py
src/models/batch_job.py
src/models/cell.py
src/models/custom_method.py
src/models/custom_report.py
src/models/dependent.py
src/models/hosted_file.py
src/models/install_script.py
src/models/logo.py
src/models/menu.py
src/models/permission.py
src/models/portal.py
src/models/role_page.py
src/models/section.py
src/models/seedrecord.py
src/models/token.py
src/models/translation.py
src/models/webpage.py
src/models/webpagedef.py
src/models/object_def/__init__.py
src/models/object_def/action.py
src/models/object_def/base.py
src/models/object_def/button.py
src/models/object_def/chart.py
src/models/object_def/conversion.py
src/models/object_def/event.py
src/models/object_def/field.py
src/models/object_def/long.py
src/models/object_def/longarr.py
src/models/object_def/object.py
src/models/object_def/process.py
src/models/object_def/relationship.py
src/models/object_def/report.py
src/models/object_def/status.py
src/models/object_def/template.py
src/models/object_def/view.py
src/models/object_def/workflow.py
src/utils/__init__.py
src/utils/customer.json
src/utils/id_dict.json
src/utils/my_json.py
src/utils/objects_dict.json
src/utils/split_tool.py
src/utils/validator.py
xmlib_to_git-1.0.7.dist-info/LICENSE
xmlib_to_git-1.0.7.dist-info/METADATA
xmlib_to_git-1.0.7.dist-info/WHEEL
xmlib_to_git-1.0.7.dist-info/entry_points.txt
xmlib_to_git-1.0.7.dist-info/top_level.txt
xmlib_to_git-1.0.7.dist-info/RECORD
