Metadata-Version: 2.1
Name: xmlib-to-git
Version: 1.0.7
Summary: Generates a Git repository from a Infinite Blue Application XML file
Author: David Dessertine
Author-email: david.dessertine@foederis.fr
License: MIT License
Classifier: Development Status :: 5 - Production/Stable
Classifier: Environment :: Console
Classifier: License :: OSI Approved :: MIT License
Classifier: Programming Language :: Python :: 3.10
Classifier: Operating System :: OS Independent
License-File: LICENSE
Requires-Dist: untangle
Requires-Dist: lxml
Requires-Dist: gitpython
Requires-Dist: unidecode
Requires-Dist: Pillow
